hcprint/__init__.py
hcprint/hcprint.py
hcprint-0.0.4.dist-info/METADATA
hcprint-0.0.4.dist-info/WHEEL
hcprint-0.0.4.dist-info/top_level.txt
hcprint-0.0.4.dist-info/RECORD
