Metadata-Version: 2.1
Name: hcprint
Version: 0.0.4
Summary: Html styled color printer for python
Home-page: https://github.com/ethankremerdojc/cprint
Author: Ethan Kremer
Author-email: ethankremer.web@gmail.com
License: UNKNOWN
Project-URL: Bug Tracker, https://github.com/ethankremerdojc/cprint/issues
Platform: UNKNOWN
Classifier: Programming Language :: Python :: 3
Classifier: License :: OSI Approved :: MIT License
Classifier: Operating System :: OS Independent
Requires-Python: >=3.4
